dynobench-0.0.4.dist-info/LICENSE
dynobench-0.0.4.dist-info/WHEEL
dynobench-0.0.4.dist-info/RECORD
dynobench-0.0.4.dist-info/METADATA
dynobench-0.0.4.dist-info/top_level.txt
dynobench.libs/libboost_program_options-38c61b5b.so.1.84.0
dynobench.libs/libccd-9b5c265e.so.2.0
dynobench.libs/libfcl-7ff5e570.so.0.7.0
dynobench.libs/libboost_stacktrace_basic-3f043e68.so.1.84.0
dynobench.libs/libboost_serialization-6847464d.so.1.84.0
dynobench/pydynobench.cpython-39-x86_64-linux-gnu.so
dynobench/hello.py
dynobench/__init__.py
dynobench/utils/__init__.py
dynobench/envs/car1_v0/bugtrap_0.yaml
dynobench/envs/car1_v0/kink_0.yaml
dynobench/envs/car1_v0/parallelpark_0.yaml
dynobench/envs/car1_v0/empty.yaml
dynobench/envs/car1_v0/parallelpark_0/idbastar_v0_opt_solution_v0.yaml
dynobench/envs/car1_v0/parallelpark_0/rrt_to_v0_guess_v0.yaml
dynobench/envs/car1_v0/parallelpark_0/idbastar_v0_db_solution_v0.yaml
dynobench/envs/car1_v0/parallelpark_0/idbastar_v0_solution_v0.yaml
dynobench/envs/car1_v0/parallelpark_0/rrt_to_v0_solution_v0.yaml
dynobench/envs/car1_v0/bugtrap_0/idbastar_v0_opt_solution_v0.yaml
dynobench/envs/car1_v0/bugtrap_0/rrt_to_v0_guess_v0.yaml
dynobench/envs/car1_v0/bugtrap_0/idbastar_v0_db_solution_v0.yaml
dynobench/envs/car1_v0/bugtrap_0/idbastar_v0_solution_v0.yaml
dynobench/envs/car1_v0/kink_0/idbastar_v0_opt_solution_v0.yaml
dynobench/envs/car1_v0/kink_0/rrt_to_v0_guess_v0.yaml
dynobench/envs/car1_v0/kink_0/idbastar_v0_db_solution_v0.yaml
dynobench/envs/car1_v0/kink_0/idbastar_v0_solution_v0.yaml
dynobench/envs/car1_v0/kink_0/rrt_to_v0_solution_v0.yaml
dynobench/envs/car1_v0/trajectories/guess_bugtrap_0_sol0.yaml
dynobench/envs/multirobot/swap1_trailer.yaml
dynobench/envs/multirobot/swap1_trailer_db.yaml
dynobench/envs/multirobot/swap1_trailer_initguess.yaml
dynobench/envs/multirobot/guess_indiv_straight.yaml
dynobench/envs/multirobot/straight.yaml
dynobench/envs/multirobot/results/swap2_unicycle2_db.yaml
dynobench/envs/multirobot/results/gen_p10_n8_9_hetero_db.yaml
dynobench/envs/multirobot/results/gen_p10_n2_1_hetero_solution.yaml
dynobench/envs/multirobot/results/swap2_unicycle2_solution.yaml
